MANIFEST.in
README.rst
setup.cfg
setup.py
atreal/__init__.py
atreal/__init__.pyc
atreal.massloader.egg-info/PKG-INFO
atreal.massloader.egg-info/SOURCES.txt
atreal.massloader.egg-info/dependency_links.txt
atreal.massloader.egg-info/entry_points.txt
atreal.massloader.egg-info/namespace_packages.txt
atreal.massloader.egg-info/not-zip-safe
atreal.massloader.egg-info/requires.txt
atreal.massloader.egg-info/top_level.txt
atreal/massloader/__init__.py
atreal/massloader/adapter.py
atreal/massloader/archives.py
atreal/massloader/configure.zcml
atreal/massloader/interfaces.py
atreal/massloader/utility.py
atreal/massloader/browser/__init__.py
atreal/massloader/browser/configure.zcml
atreal/massloader/browser/controlpanel.py
atreal/massloader/browser/massloader.pt
atreal/massloader/browser/massloader.py
atreal/massloader/browser/massloader_icon.png
atreal/massloader/locales/atreal.massloader.pot
atreal/massloader/locales/de/LC_MESSAGES/atreal.massloader.po
atreal/massloader/locales/fr/LC_MESSAGES/atreal.massloader.po
atreal/massloader/locales/nl/LC_MESSAGES/atreal.massloader.po
atreal/massloader/profiles/default/actionicons.xml
atreal/massloader/profiles/default/actions.xml
atreal/massloader/profiles/default/browserlayer.xml
atreal/massloader/profiles/default/controlpanel.xml
atreal/massloader/profiles/default/metadata.xml
atreal/massloader/profiles/default/rolemap.xml
docs/HISTORY.txt
docs/INSTALL.txt
docs/LICENSE.GPL
docs/LICENSE.txt