Metadata-Version: 1.1
Name: atreal.massloader
Version: 3.1.2
Summary: Add an action to import zip files.
Home-page: https://svn.plone.org/svn/collective/atreal.massloader/trunk
Author: atReal
Author-email: contact@atreal.net
License: GPL
Platform: UNKNOWN
Classifier: Framework :: Plone
Classifier: Programming Language :: Python
Classifier: Topic :: Software Development :: Libraries :: Python Modules
